get_tense/__init__.py
get_tense/get_tense.py
get_tense/past_tense_verbs
get_tense-0.0.4.data/data/get_tense/past_tense_verbs
get_tense-0.0.4.dist-info/METADATA
get_tense-0.0.4.dist-info/WHEEL
get_tense-0.0.4.dist-info/top_level.txt
get_tense-0.0.4.dist-info/RECORD
